{"stats":{"minecraft:mined":{"minecraft:white_bed":8,"minecraft:crafting_table":1},"minecraft:custom":{"minecraft:time_since_rest":35334,"minecraft:crouch_one_cm":210,"lootr:looted_stat":1,"minecraft:play_time":138630,"minecraft:damage_taken":140,"minecraft:walk_one_cm":368294,"minecraft:sneak_time":551,"minecraft:walk_under_water_one_cm":3181,"minecraft:drop":1,"minecraft:boat_one_cm":356050,"minecraft:interact_with_lectern":2,"minecraft:jump":515,"minecraft:walk_on_water_one_cm":10774,"minecraft:leave_game":2,"minecraft:time_since_death":138630,"minecraft:sleep_in_bed":8,"minecraft:climb_one_cm":3235,"minecraft:total_world_time":138630,"minecraft:swim_one_cm":1718,"minecraft:fall_one_cm":6268,"minecraft:talked_to_villager":1,"minecraft:interact_with_crafting_table":1,"minecraft:fly_one_cm":157},"minecraft:dropped":{"minecraft:oak_boat":1},"minecraft:crafted":{"minecraft:oak_boat":1,"minecraft:oak_planks":12,"minecraft:crafting_table":1},"minecraft:picked_up":{"minecraft:crafting_table":1,"minecraft:gravel":2,"alexsmobs:cachalot_whale_tooth":1,"minecraft:oak_boat":5,"supplementaries:quiver":1,"minecraft:white_bed":8},"minecraft:used":{"minecraft:crafting_table":2,"minecraft:baked_potato":3,"minecraft:oak_boat":4,"minecraft:white_bed":16}},"DataVersion":3465}